hepconvert/__init__.py
hepconvert/__main__.py
hepconvert/_utils.py
hepconvert/_version.py
hepconvert/_version.pyi
hepconvert/copy_root.py
hepconvert/histogram_adding.py
hepconvert/merge.py
hepconvert/parquet_to_root.py
hepconvert/py.typed
hepconvert/root_to_parquet.py
hepconvert-1.3.7.dist-info/METADATA
hepconvert-1.3.7.dist-info/WHEEL
hepconvert-1.3.7.dist-info/entry_points.txt
hepconvert-1.3.7.dist-info/licenses/LICENSE
hepconvert-1.3.7.dist-info/RECORD
